pyz3r/__init__.py
pyz3r/alttpr.py
pyz3r/customizer.py
pyz3r/exceptions.py
pyz3r/misc.py
pyz3r/mystery.py
pyz3r/rom.py
pyz3r/sm.py
pyz3r/smvaria.py
pyz3r/spoiler.py
pyz3r/ext/__init__.py
pyz3r/ext/priestmode.py
pyz3r-6.1.0.dist-info/LICENSE
pyz3r-6.1.0.dist-info/METADATA
pyz3r-6.1.0.dist-info/WHEEL
pyz3r-6.1.0.dist-info/top_level.txt
pyz3r-6.1.0.dist-info/RECORD
