Metadata-Version: 2.1
Name: pyz3r
Version: 6.1.0
Summary: A python module for interacting with the web API of various randomizers, such as https://alttpr.com or https://samus.link.
Home-page: https://github.com/tcprescott/pyz3r
Author: Thomas Prescott
Author-email: tcprescott@gmail.com
Classifier: Programming Language :: Python :: 3
Classifier: Programming Language :: Python :: 3.6
Classifier: Programming Language :: Python :: 3.7
Classifier: Programming Language :: Python :: 3.8
Classifier: License :: OSI Approved :: Apache Software License
Classifier: Development Status :: 5 - Production/Stable
Classifier: Operating System :: OS Independent
License-File: LICENSE
Requires-Dist: aiofiles
Requires-Dist: aiohttp
Requires-Dist: python-bps-continued >=7
Requires-Dist: slugid
Requires-Dist: tenacity
